objectways/__init__.py
objectways/newton.py
newton_api_client-1.2.2.dist-info/LICENSE
newton_api_client-1.2.2.dist-info/METADATA
newton_api_client-1.2.2.dist-info/WHEEL
newton_api_client-1.2.2.dist-info/top_level.txt
newton_api_client-1.2.2.dist-info/RECORD
