Metadata-Version: 2.1
Name: newton-api-client
Version: 1.2.2
Summary: Python api client - https://api.objectways.com/docs
Home-page: https://github.com/deepalirajale/newton-api
Author: Objectways
Author-email: tech-support@objectways.com
Project-URL: Bug Tracker, https://github.com/deepalirajale/newton-api/issues
Classifier: Programming Language :: Python :: 3
Classifier: License :: OSI Approved :: MIT License
Classifier: Operating System :: OS Independent
Requires-Python: >=3.6
License-File: LICENSE
